sgrkannada/__init__.py
sgrkannada-1.1.0.dist-info/METADATA
sgrkannada-1.1.0.dist-info/WHEEL
sgrkannada-1.1.0.dist-info/top_level.txt
sgrkannada-1.1.0.dist-info/RECORD
